baytos/__init__.py
baytos/claro/__init__.py
baytos/claro/client.py
baytos/claro/context.py
baytos/claro/exceptions.py
baytos/claro/models.py
baytos/claro/utils.py
baytos_claro-0.0.1.dist-info/licenses/LICENSE
baytos_claro-0.0.1.dist-info/METADATA
baytos_claro-0.0.1.dist-info/WHEEL
baytos_claro-0.0.1.dist-info/top_level.txt
baytos_claro-0.0.1.dist-info/RECORD
