Metadata-Version: 2.4
Name: baytos-claro
Version: 0.0.1
Summary: Python SDK for Claro by Bayt OS
Author-email: "Bayt, Inc." <support@baytos.ai>
License-Expression: MIT
Project-URL: Homepage, https://baytos.ai
Project-URL: Documentation, https://docs.baytos.ai
Project-URL: Issues, https://docs.baytos.ai/support
Keywords: ai,llm,prompts,sdk,baytos,claro
Classifier: Development Status :: 3 - Alpha
Classifier: Intended Audience :: Developers
Classifier: Operating System :: OS Independent
Classifier: Topic :: Software Development :: Libraries :: Python Modules
Classifier: Programming Language :: Python :: 3
Classifier: Programming Language :: Python :: 3.8
Classifier: Programming Language :: Python :: 3.9
Classifier: Programming Language :: Python :: 3.10
Classifier: Programming Language :: Python :: 3.11
Classifier: Programming Language :: Python :: 3.12
Classifier: Programming Language :: Python :: 3.13
Requires-Python: >=3.8
License-File: LICENSE
Requires-Dist: requests>=2.25.0
Provides-Extra: dev
Requires-Dist: pytest>=6.0; extra == "dev"
Requires-Dist: pytest-cov>=2.0; extra == "dev"
Requires-Dist: pytest-mock>=3.0; extra == "dev"
Requires-Dist: pytest-timeout>=2.0; extra == "dev"
Requires-Dist: python-dotenv>=0.19.0; extra == "dev"
Requires-Dist: black>=22.0; extra == "dev"
Requires-Dist: flake8>=4.0; extra == "dev"
Requires-Dist: flake8-docstrings>=1.6; extra == "dev"
Requires-Dist: mypy>=0.900; extra == "dev"
Requires-Dist: types-requests; extra == "dev"
Requires-Dist: pip-audit>=2.0; extra == "dev"
Requires-Dist: build>=0.7; extra == "dev"
Requires-Dist: twine>=3.0; extra == "dev"
Requires-Dist: tox>=4.0; extra == "dev"
Dynamic: license-file
